python_solarfrontier/__init__.py
python_solarfrontier/api.py
python_solarfrontier/const.py
python_solarfrontier/utils.py
tests/__init__.py
tests/test_api.py
tests/test_utils.py
python_solarfrontier-0.1.1.dist-info/LICENCE
python_solarfrontier-0.1.1.dist-info/METADATA
python_solarfrontier-0.1.1.dist-info/WHEEL
python_solarfrontier-0.1.1.dist-info/top_level.txt
python_solarfrontier-0.1.1.dist-info/RECORD
