Metadata-Version: 2.1
Name: python-solarfrontier
Version: 0.1.1
Summary: Library to communicate with Solar Frotier inverters
Home-page: https://github.com/ernestasga/python-solarfrontier
Author: ernestasga
Classifier: Programming Language :: Python :: 3
Classifier: License :: OSI Approved :: MIT License
Classifier: Operating System :: OS Independent
Requires-Python: >=3.8
License-File: LICENCE
